LICENSE
MANIFEST.in
README.md
pyproject.toml
requirements.txt
requirements_dev.txt
requirements_test.txt
esphome/__init__.py
esphome/__main__.py
esphome/automation.py
esphome/codegen.py
esphome/config.py
esphome/config_helpers.py
esphome/config_validation.py
esphome/const.py
esphome/coroutine.py
esphome/cpp_generator.py
esphome/cpp_helpers.py
esphome/cpp_types.py
esphome/enum.py
esphome/espota2.py
esphome/external_files.py
esphome/final_validate.py
esphome/git.py
esphome/helpers.py
esphome/loader.py
esphome/log.py
esphome/mqtt.py
esphome/pins.py
esphome/platformio_api.py
esphome/schema_extractors.py
esphome/storage_json.py
esphome/types.py
esphome/util.py
esphome/voluptuous_schema.py
esphome/vscode.py
esphome/wizard.py
esphome/writer.py
esphome/yaml_util.py
esphome/zeroconf.py
esphome/components/__init__.py
esphome/components/a01nyub/__init__.py
esphome/components/a01nyub/a01nyub.cpp
esphome/components/a01nyub/a01nyub.h
esphome/components/a01nyub/sensor.py
esphome/components/a02yyuw/__init__.py
esphome/components/a02yyuw/a02yyuw.cpp
esphome/components/a02yyuw/a02yyuw.h
esphome/components/a02yyuw/sensor.py
esphome/components/a4988/__init__.py
esphome/components/a4988/a4988.cpp
esphome/components/a4988/a4988.h
esphome/components/a4988/stepper.py
esphome/components/absolute_humidity/__init__.py
esphome/components/absolute_humidity/absolute_humidity.cpp
esphome/components/absolute_humidity/absolute_humidity.h
esphome/components/absolute_humidity/sensor.py
esphome/components/ac_dimmer/__init__.py
esphome/components/ac_dimmer/ac_dimmer.cpp
esphome/components/ac_dimmer/ac_dimmer.h
esphome/components/ac_dimmer/output.py
esphome/components/adalight/__init__.py
esphome/components/adalight/adalight_light_effect.cpp
esphome/components/adalight/adalight_light_effect.h
esphome/components/adc/__init__.py
esphome/components/adc/adc_sensor.h
esphome/components/adc/adc_sensor_common.cpp
esphome/components/adc/adc_sensor_esp32.cpp
esphome/components/adc/adc_sensor_esp8266.cpp
espjhome.egg-info/PKG-INFO
espjhome.egg-info/SOURCES.txt
espjhome.egg-info/dependency_links.txt
espjhome.egg-info/entry_points.txt
espjhome.egg-info/not-zip-safe
espjhome.egg-info/requires.txt
espjhome.egg-info/top_level.txt